library_of_life/__init__.py
library_of_life/gbif_root.py
library_of_life/literature/__init__.py
library_of_life/literature/literature.py
library_of_life/maps/__init__.py
library_of_life/maps/maps.py
library_of_life/occurrence/__init__.py
library_of_life/occurrence/country_usages.py
library_of_life/occurrence/download_formats.py
library_of_life/occurrence/download_stats.py
library_of_life/occurrence/downloads.py
library_of_life/occurrence/gadm_regions.py
library_of_life/occurrence/inventories.py
library_of_life/occurrence/metrics.py
library_of_life/occurrence/organization_usages.py
library_of_life/occurrence/search.py
library_of_life/occurrence/single_occurrence.py
library_of_life/registry/__init__.py
library_of_life/registry/collections.py
library_of_life/registry/datasets.py
library_of_life/registry/derived_datasets.py
library_of_life/registry/institutions.py
library_of_life/registry/institutions_and_collections.py
library_of_life/registry/networks.py
library_of_life/registry/participant_nodes.py
library_of_life/registry/publishing_orgs.py
library_of_life/registry/tech_installations.py
library_of_life/species/__init__.py
library_of_life/species/name_parser.py
library_of_life/species/name_search.py
library_of_life/species/name_usage.py
library_of_life/utils/__init__.py
library_of_life/utils/http_client.py
library_of_life/vocabulary/__init__.py
library_of_life/vocabulary/concepts.py
library_of_life/vocabulary/languages.py
library_of_life/vocabulary/tags.py
library_of_life/vocabulary/vocabularies.py
library_of_life-0.4.2.dist-info/LICENSE
library_of_life-0.4.2.dist-info/METADATA
library_of_life-0.4.2.dist-info/WHEEL
library_of_life-0.4.2.dist-info/RECORD
