Metadata-Version: 2.1
Name: library-of-life
Version: 0.4.2
Summary: A python client for the Global Biological Information Facility (GBIF) API
Home-page: https://github.com/SpyderRex/library-of-life
License: MIT
Keywords: API,requests,client,gbif,biodata,biology,life,species
Author: Spyder Rex
Author-email: billyjohnsonauthor@gmail.com
Requires-Python: >=3.8,<4.0
Classifier: License :: OSI Approved :: MIT License
Classifier: Operating System :: OS Independent
Classifier: Programming Language :: Python :: 3
Classifier: Programming Language :: Python :: 3.8
Classifier: Programming Language :: Python :: 3.9
Classifier: Programming Language :: Python :: 3.10
Classifier: Programming Language :: Python :: 3.11
Classifier: Programming Language :: Python :: 3.12
Requires-Dist: pillow (==10.2.0)
Requires-Dist: requests (>=2.26.0,<3.0.0)
Requires-Dist: requests-cache (==1.2.0)
Project-URL: Repository, https://github.com/SpyderRex/library-of-life
